emdata_tools/__init__.py
emdata_tools/__version__.py
emdata_tools/eureka.py
emdata_tools/log.py
emdata_tools/utils.py
emdata_tools-1.0.1.dist-info/LICENSE
emdata_tools-1.0.1.dist-info/METADATA
emdata_tools-1.0.1.dist-info/WHEEL
emdata_tools-1.0.1.dist-info/top_level.txt
emdata_tools-1.0.1.dist-info/RECORD
